omeschema/__init__.py
omeschema/schemas/2016-06/ome.xsd
schemas/2016-06/ome.xsd
ome_schema-0.1.0.dist-info/LICENSE
ome_schema-0.1.0.dist-info/METADATA
ome_schema-0.1.0.dist-info/WHEEL
ome_schema-0.1.0.dist-info/top_level.txt
ome_schema-0.1.0.dist-info/RECORD
