Metadata-Version: 2.1
Name: ome-schema
Version: 0.1.0
Summary: A Python package for accessing local OME schema files
Home-page: https://github.com/jason-weirather/ome-schema
Author: Jason L Weirather
Author-email: jason.weirather@gmail.com
Classifier: Development Status :: 3 - Alpha
Classifier: Intended Audience :: Developers
Classifier: License :: OSI Approved :: MIT License
Classifier: Programming Language :: Python
Classifier: Programming Language :: Python :: 3
Classifier: Programming Language :: Python :: 3.6
Classifier: Programming Language :: Python :: 3.7
Classifier: Programming Language :: Python :: 3.8
Classifier: Programming Language :: Python :: 3.9
License-File: LICENSE
